aliyun_encryption_sdk/__init__.py
aliyun_encryption_sdk/client.py
aliyun_encryption_sdk/constants.py
aliyun_encryption_sdk/model.py
aliyun_encryption_sdk/cache/__init__.py
aliyun_encryption_sdk/cache/base.py
aliyun_encryption_sdk/cache/local.py
aliyun_encryption_sdk/ckm/__init__.py
aliyun_encryption_sdk/ckm/base.py
aliyun_encryption_sdk/ckm/cache.py
aliyun_encryption_sdk/ckm/default.py
aliyun_encryption_sdk/handle/__init__.py
aliyun_encryption_sdk/handle/encryption.py
aliyun_encryption_sdk/handle/format.py
aliyun_encryption_sdk/kms/__init__.py
aliyun_encryption_sdk/kms/kms.py
aliyun_encryption_sdk/provider/__init__.py
aliyun_encryption_sdk/provider/base.py
aliyun_encryption_sdk/provider/default.py
aliyun_encryption_sdk/provider/secret_manager.py
aliyun_encryption_sdk/provider/signature/__init__.py
aliyun_encryption_sdk/provider/signature/base.py
aliyun_encryption_sdk/provider/signature/verifier.py
bestv_aliyun_encryption_sdk/__init__.py
bestv_aliyun_encryption_sdk/client.py
bestv_aliyun_encryption_sdk/constants.py
bestv_aliyun_encryption_sdk/model.py
bestv_aliyun_encryption_sdk/cache/__init__.py
bestv_aliyun_encryption_sdk/cache/base.py
bestv_aliyun_encryption_sdk/cache/local.py
bestv_aliyun_encryption_sdk/ckm/__init__.py
bestv_aliyun_encryption_sdk/ckm/base.py
bestv_aliyun_encryption_sdk/ckm/cache.py
bestv_aliyun_encryption_sdk/ckm/default.py
bestv_aliyun_encryption_sdk/handle/__init__.py
bestv_aliyun_encryption_sdk/handle/encryption.py
bestv_aliyun_encryption_sdk/handle/format.py
bestv_aliyun_encryption_sdk/kms/__init__.py
bestv_aliyun_encryption_sdk/kms/kms.py
bestv_aliyun_encryption_sdk/provider/__init__.py
bestv_aliyun_encryption_sdk/provider/base.py
bestv_aliyun_encryption_sdk/provider/default.py
bestv_aliyun_encryption_sdk/provider/secret_manager.py
bestv_aliyun_encryption_sdk/provider/signature/__init__.py
bestv_aliyun_encryption_sdk/provider/signature/base.py
bestv_aliyun_encryption_sdk/provider/signature/verifier.py
bestv_aliyun_encryption_sdk-0.1.2.dist-info/LICENSE
bestv_aliyun_encryption_sdk-0.1.2.dist-info/METADATA
bestv_aliyun_encryption_sdk-0.1.2.dist-info/WHEEL
bestv_aliyun_encryption_sdk-0.1.2.dist-info/top_level.txt
bestv_aliyun_encryption_sdk-0.1.2.dist-info/RECORD
