Metadata-Version: 2.1
Name: bestv-aliyun-encryption-sdk
Version: 0.1.2
Summary: Alibaba Cloud Encryption SDK implementation for Python
Author: Alibaba Cloud
Maintainer: Alibaba Cloud
Keywords: bestv-aliyun-encryption-sdk,Alibaba Cloud KMS Encryption SDK
Classifier: Development Status :: 5 - Production/Stable
Classifier: Programming Language :: Python
Classifier: Programming Language :: Python :: 2
Classifier: Programming Language :: Python :: 2.7
Classifier: Programming Language :: Python :: 3
Classifier: Programming Language :: Python :: 3.4
Classifier: Programming Language :: Python :: 3.5
Classifier: Programming Language :: Python :: 3.6
Classifier: Programming Language :: Python :: 3.7
Classifier: Programming Language :: Python :: Implementation :: CPython
Classifier: Topic :: Security
Classifier: Topic :: Security :: Cryptography
License-File: LICENSE
Requires-Dist: aliyun-python-sdk-kms (==2.14.0)
Requires-Dist: attrs (==20.3.0)
Requires-Dist: cryptography (==3.2.1)
Requires-Dist: asn1crypto (==1.4.0)
Requires-Dist: six (==1.15.0)
Requires-Dist: aliyun-python-sdk-core (==2.13.30)
